README.md
setup.py
src/sentry_10_dingding.egg-info/PKG-INFO
src/sentry_10_dingding.egg-info/SOURCES.txt
src/sentry_10_dingding.egg-info/dependency_links.txt
src/sentry_10_dingding.egg-info/entry_points.txt
src/sentry_10_dingding.egg-info/not-zip-safe
src/sentry_10_dingding.egg-info/requires.txt
src/sentry_10_dingding.egg-info/top_level.txt
src/sentry_dingding/__init__.py
src/sentry_dingding/forms.py
src/sentry_dingding/plugin.py